Metadata-Version: 2.1
Name: funcionesOmar
Version: 0.5
Summary: Ejercicio tema 13
Home-page: https://github.com/RobertoCoronaEscamilla/libreria_rc
Download-URL: https://github.com/RobertoCoronaEscamilla/libreria_rc.git
Author: Omar
Author-email: xxx@gmail.com
License: MIT
Keywords: mates,par,impar
Classifier: Development Status :: 3 - Alpha
Classifier: Intended Audience :: Developers
Classifier: Topic :: Software Development :: Build Tools
Classifier: License :: OSI Approved :: MIT License
Classifier: Programming Language :: Python :: 3
Classifier: Programming Language :: Python :: 3.4
Classifier: Programming Language :: Python :: 3.5
Classifier: Programming Language :: Python :: 3.6
License-File: LICENSE.txt
Requires-Dist: pytest
